{"name":"ClockTree","element":[{"name":"HSIRC","Elementtype":"fixedSource","sources":[{"output":{"to":"HSIDiv"}},{"output":{"to":"HSI_DIV"}}],"reference":{"FixedNumber":64000000}},{"name":"HSIDiv","Elementtype":"devisor","sources":[{"input":{"from":"HSIRC"}},{"output":{"to":"SysClkSource"}},{"output":{"to":"PLLSource"}},{"output":{"to":"CKPERSource"}},{"output":{"to":"MCO1Mult"}},{"output":{"to":"SPDIFMult"}},{"output":{"to":"SPI45Mult"}},{"output":{"to":"I2C1Mult"}},{"output":{"to":"USART1Mult"}},{"output":{"to":"USART234578Mult"}},{"output":{"to":"SPI6Mult"}},{"output":{"to":"I2C23Mult"}},{"output":{"to":"LPUART1Mult"}},{"output":{"to":"ADFMult"}}],"reference":{"NumberList":{"default":1e0,"list":[1e0,2e0,4e0,8e0]}}},{"name":"HSEOSC","Elementtype":"variedSource","sources":[{"output":{"to":"SysClkSource"}},{"output":{"to":"HSERTCDevisor"}},{"output":{"to":"PLLSource"}},{"output":{"to":"CKPERSource"}},{"output":{"to":"MCO1Mult"}},{"output":{"to":"MCO2Mult"}},{"output":{"to":"FDCANMult"}},{"output":{"to":"SPI45Mult"}},{"output":{"to":"SPI6Mult"}},{"output":{"to":"HSEUSBPHYDevisor"}},{"output":{"to":"USBPHYCLKMux"}},{"output":{"to":"USBOCLKMux"}},{"output":{"to":"ETHPHYMult"}},{"output":{"to":"ETH1Mult"}}],"reference":{"Number":{"default":24000000,"max":50000000,"min":4000000}}},{"name":"LSIRC","Elementtype":"variedSource","sources":[{"output":{"to":"IWDGOutput"}},{"output":{"to":"RTCClkSource"}},{"output":{"to":"LPTIM1Mult"}},{"output":{"to":"LPTIM23Mult"}},{"output":{"to":"LPTIM45Mult"}},{"output":{"to":"CECMult"}}],"reference":{"Number":{"default":32000,"max":32600,"min":31400}}},{"name":"LSEOSC","Elementtype":"variedSource","sources":[{"output":{"to":"RTCClkSource"}},{"output":{"to":"MCO1Mult"}},{"output":{"to":"CECMult"}},{"output":{"to":"LPTIM1Mult"}},{"output":{"to":"LPTIM23Mult"}},{"output":{"to":"LPTIM45Mult"}},{"output":{"to":"LPUART1Mult"}},{"output":{"to":"USART234578Mult"}},{"output":{"to":"USART1Mult"}},{"output":{"to":"DTSOutput"}}],"reference":{"Number":{"default":32768,"max":1000000,"min":0}}},{"name":"CSIRC","Elementtype":"fixedSource","sources":[{"output":{"to":"SysClkSource"}},{"output":{"to":"PLLSource"}},{"output":{"to":"CKPERSource"}},{"output":{"to":"MCO2Mult"}},{"output":{"to":"SPI45Mult"}},{"output":{"to":"I2C1Mult"}},{"output":{"to":"USART1Mult"}},{"output":{"to":"USART234578Mult"}},{"output":{"to":"SPI6Mult"}},{"output":{"to":"I2C23Mult"}},{"output":{"to":"LPUART1Mult"}},{"output":{"to":"CSICECDevisor"}},{"output":{"to":"ADFMult"}}],"reference":{"FixedNumber":4000000}},{"name":"RC48","Elementtype":"fixedSource","sources":[{"output":{"to":"MCO1Mult"}},{"output":{"to":"USBOCLKMux"}},{"output":{"to":"RNGOutput"}}],"reference":{"FixedNumber":48000000}},{"name":"I2S_CKIN","Elementtype":"variedSource","sources":[{"output":{"to":"SPI1Mult"}},{"output":{"to":"SPI23Mult"}},{"output":{"to":"SAI1Mult"}},{"output":{"to":"SAI2Mult"}},{"output":{"to":"ADFMult"}}],"reference":{"FixedNumber":12288000}},{"name":"Dig_CKIN","Elementtype":"variedSource","sources":[{"output":{"to":"ETH1Mult"}}],"reference":{"FixedNumber":12288000}},{"name":"SysClkSource","Elementtype":"multiplexor","sources":[{"input":{"from":"HSIDiv"}},{"input":{"from":"CSIRC"}},{"input":{"from":"HSEOSC"}},{"input":{"from":"DIVP1"}},{"output":{"to":"SysCLKOutput"}}],"reference":{"Input":{"DefaultInput":"HSIDiv"}}},{"name":"SysCLKOutput","Elementtype":"output","sources":[{"input":{"from":"SysClkSource"}},{"output":{"to":"CPRE"}},{"output":{"to":"MCO2Mult"}}],"reference":{"Number":{"default":96000000,"max":600000000,"min":0}}},{"name":"MCO1Mult","Elementtype":"multiplexor","sources":[{"input":{"from":"HSIDiv"}},{"input":{"from":"HSEOSC"}},{"input":{"from":"LSEOSC"}},{"input":{"from":"RC48"}},{"input":{"from":"DIVQ1"}},{"output":{"to":"MCO1Div"}}],"reference":{"Input":{"DefaultInput":"HSIDiv"}}},{"name":"MCO1Div","Elementtype":"devisor","sources":[{"input":{"from":"MCO1Mult"}},{"output":{"to":"MCO1Pin"}}],"reference":{"NumberList":{"default":1e0,"list":[1e0,2e0,3e0,4e0,5e0,6e0,7e0,8e0,9e0,1e1,1.1e1,1.2e1,1.3e1,1.4e1,1.5e1]}}},{"name":"MCO1Pin","Elementtype":"output","sources":[{"input":{"from":"MCO1Div"}}],"reference":{"FixedNumber":96000000}},{"name":"MCO2Mult","Elementtype":"multiplexor","sources":[{"input":{"from":"SysCLKOutput"}},{"input":{"from":"DIVP2"}},{"input":{"from":"HSEOSC"}},{"input":{"from":"DIVP1"}},{"input":{"from":"CSIRC"}},{"input":{"from":"LSIRC"}},{"output":{"to":"MCO2Div"}}],"reference":{"Input":{"DefaultInput":"SysCLKOutput"}}},{"name":"MCO2Div","Elementtype":"devisor","sources":[{"input":{"from":"MCO2Mult"}},{"output":{"to":"MCO2Pin"}}],"reference":{"NumberList":{"default":1e0,"list":[1e0,2e0,3e0,4e0,5e0,6e0,7e0,8e0,9e0,1e1,1.1e1,1.2e1,1.3e1,1.4e1,1.5e1]}}},{"name":"MCO2Pin","Elementtype":"output","sources":[{"input":{"from":"MCO2Div"}}],"reference":{"FixedNumber":96000000}},{"name":"CPRE","Elementtype":"devisor","sources":[{"input":{"from":"SysCLKOutput"}},{"output":{"to":"CPREOutput"}}],"reference":{"NumberList":{"default":1e0,"list":[1e0,2e0,4e0,8e0,1.6e1,6.4e1,1.28e2,2.56e2,5.12e2]}}},{"name":"CPREOutput","Elementtype":"activeOutput","sources":[{"input":{"from":"CPRE"}},{"output":{"to":"TPIUPrescaler"}},{"output":{"to":"CpuClockOutput"}},{"output":{"to":"CortexPrescaler"}},{"output":{"to":"BMPRE"}}],"reference":{"Number":{"default":12288000,"max":600000000,"min":0}}},{"name":"TPIUPrescaler","Elementtype":"devisor","sources":[{"input":{"from":"CPREOutput"}},{"output":{"to":"TPIUOutput"}}],"reference":{"NumberList":{"default":3e0,"list":[3e0]}}},{"name":"TPIUOutput","Elementtype":"activeOutput","sources":[{"input":{"from":"TPIUPrescaler"}}],"reference":{"FixedNumber":96000000}},{"name":"CpuClockOutput","Elementtype":"activeOutput","sources":[{"input":{"from":"CPREOutput"}}],"reference":{"Number":{"default":96000000,"max":600000000,"min":0}}},{"name":"CortexPrescaler","Elementtype":"devisor","sources":[{"input":{"from":"CPREOutput"}},{"output":{"to":"CortexSysOutput"}}],"reference":{"NumberList":{"default":1e0,"list":[1e0,8e0]}}},{"name":"CortexSysOutput","Elementtype":"activeOutput","sources":[{"input":{"from":"CortexPrescaler"}}],"reference":{"Number":{"default":96000000,"max":600000000,"min":0}}},{"name":"BMPRE","Elementtype":"devisor","sources":[{"input":{"from":"CPREOutput"}},{"output":{"to":"AHBOutput"}}],"reference":{"NumberList":{"default":1e0,"list":[1e0,2e0,4e0,8e0,1.6e1,6.4e1,1.28e2,2.56e2,5.12e2]}}},{"name":"AHBOutput","Elementtype":"activeOutput","sources":[{"input":{"from":"BMPRE"}},{"output":{"to":"AXIClockOutput"}},{"output":{"to":"AHB5Output"}},{"output":{"to":"PPRE5"}},{"output":{"to":"AHB1234Output"}},{"output":{"to":"PPRE1"}},{"output":{"to":"PPRE2"}},{"output":{"to":"PPRE4"}},{"output":{"to":"ADFMult"}}],"reference":{"Number":{"default":12288000,"max":300000000,"min":0}}},{"name":"AXIClockOutput","Elementtype":"activeOutput","sources":[{"input":{"from":"AHBOutput"}}],"reference":{"Number":{"default":96000000,"max":300000000,"min":0}}},{"name":"AHB5Output","Elementtype":"activeOutput","sources":[{"input":{"from":"AHBOutput"}},{"output":{"to":"XSPI1Mult"}},{"output":{"to":"XSPI2Mult"}},{"output":{"to":"FMCMult"}}],"reference":{"Number":{"default":96000000,"max":300000000,"min":0}}},{"name":"PPRE5","Elementtype":"devisor","sources":[{"input":{"from":"AHBOutput"}},{"output":{"to":"APB5Output"}}],"reference":{"NumberList":{"default":1e0,"list":[1e0,2e0,4e0,8e0,1.6e1]}}},{"name":"APB5Output","Elementtype":"activeOutput","sources":[{"input":{"from":"PPRE5"}}],"reference":{"Number":{"default":96000000,"max":150000000,"min":0}}},{"name":"AHB1234Output","Elementtype":"activeOutput","sources":[{"input":{"from":"AHBOutput"}}],"reference":{"Number":{"default":96000000,"max":300000000,"min":0}}},{"name":"PPRE1","Elementtype":"devisor","sources":[{"input":{"from":"AHBOutput"}},{"output":{"to":"APB1Output"}},{"output":{"to":"Tim1Mul"}},{"output":{"to":"SPI45Mult"}},{"output":{"to":"LPTIM1Mult"}},{"output":{"to":"I2C1Mult"}},{"output":{"to":"USART234578Mult"}}],"reference":{"NumberList":{"default":1e0,"list":[1e0,2e0,4e0,8e0,1.6e1]}}},{"name":"APB1Output","Elementtype":"activeOutput","sources":[{"input":{"from":"PPRE1"}}],"reference":{"Number":{"default":96000000,"max":150000000,"min":0}}},{"name":"Tim1Mul","Elementtype":"multiplicator","sources":[{"input":{"from":"PPRE1"}},{"output":{"to":"Tim1Output"}}],"reference":{"FixedNumber":2}},{"name":"Tim1Output","Elementtype":"output","sources":[{"input":{"from":"Tim1Mul"}}],"reference":{"FixedNumber":96000000}},{"name":"PPRE2","Elementtype":"devisor","sources":[{"input":{"from":"AHBOutput"}},{"output":{"to":"APB2Output"}},{"output":{"to":"USART1Mult"}},{"output":{"to":"Tim2Mul"}}],"reference":{"NumberList":{"default":1e0,"list":[1e0,2e0,4e0,8e0,1.6e1]}}},{"name":"APB2Output","Elementtype":"activeOutput","sources":[{"input":{"from":"PPRE2"}}],"reference":{"Number":{"default":96000000,"max":150000000,"min":0}}},{"name":"Tim2Mul","Elementtype":"multiplicator","sources":[{"input":{"from":"PPRE2"}},{"output":{"to":"Tim2Output"}}],"reference":{"FixedNumber":2}},{"name":"Tim2Output","Elementtype":"output","sources":[{"input":{"from":"Tim2Mul"}}],"reference":{"FixedNumber":96000000}},{"name":"PPRE4","Elementtype":"devisor","sources":[{"input":{"from":"AHBOutput"}},{"output":{"to":"APB4Output"}}],"reference":{"NumberList":{"default":1e0,"list":[1e0,2e0,4e0,8e0,1.6e1]}}},{"name":"APB4Output","Elementtype":"activeOutput","sources":[{"input":{"from":"PPRE4"}}],"reference":{"Number":{"default":96000000,"max":150000000,"min":0}}},{"name":"PLLSource","Elementtype":"multiplexor","sources":[{"input":{"from":"HSIDiv"}},{"input":{"from":"CSIRC"}},{"input":{"from":"HSEOSC"}},{"output":{"to":"DIVM1"}},{"output":{"to":"DIVM2"}},{"output":{"to":"DIVM3"}}],"reference":{"Input":{"DefaultInput":"HSIDiv"}}},{"name":"CKPERSource","Elementtype":"multiplexor","sources":[{"input":{"from":"HSIDiv"}},{"input":{"from":"CSIRC"}},{"input":{"from":"HSEOSC"}},{"output":{"to":"SPI1Mult"}},{"output":{"to":"SPI23Mult"}},{"output":{"to":"SAI1Mult"}},{"output":{"to":"LPTIM1Mult"}},{"output":{"to":"SAI2Mult"}},{"output":{"to":"ADCMult"}},{"output":{"to":"LPTIM23Mult"}},{"output":{"to":"LPTIM45Mult"}},{"output":{"to":"CKPERoutput"}}],"reference":{"Input":{"DefaultInput":"HSIDiv"}}},{"name":"CKPERoutput","Elementtype":"output","sources":[{"input":{"from":"CKPERSource"}}],"reference":{"FixedNumber":12288000}},{"name":"DIVM1","Elementtype":"devisor","sources":[{"input":{"from":"PLLSource"}},{"output":{"to":"DIVN1"}}],"reference":{"Number":{"default":32,"max":63,"min":1}}},{"name":"DIVM2","Elementtype":"devisor","sources":[{"input":{"from":"PLLSource"}},{"output":{"to":"DIVN2"}}],"reference":{"Number":{"default":32,"max":63,"min":1}}},{"name":"DIVM3","Elementtype":"devisor","sources":[{"input":{"from":"PLLSource"}},{"output":{"to":"DIVN3"}}],"reference":{"Number":{"default":32,"max":63,"min":1}}},{"name":"DIVN1","Elementtype":"multiplicatorFrac","sources":[{"input":{"from":"DIVM1"}},{"input":{"from":"PLLFRACN"}},{"output":{"to":"DIVP1"}},{"output":{"to":"DIVQ1"}},{"output":{"to":"DIVR1"}},{"output":{"to":"DIVS1"}},{"output":{"to":"DIVT1"}}],"reference":{"Number":{"default":128,"max":420,"min":8}}},{"name":"PLLFRACN","Elementtype":"fractional","sources":[{"output":{"to":"DIVN1"}}],"reference":{"Number":{"default":0,"max":8191,"min":0}}},{"name":"DIVP1","Elementtype":"devisor","sources":[{"input":{"from":"DIVN1"}},{"output":{"to":"MCO2Mult"}},{"output":{"to":"SysClkSource"}}],"reference":{"NumberList":{"default":2e0,"list":[1e0,2e0,4e0,6e0,8e0,1e1,1.2e1,1.4e1,1.6e1,1.8e1,2e1,2.2e1,2.4e1,2.6e1,2.8e1,3e1,3.2e1,3.4e1,3.6e1,3.8e1,4e1,4.2e1,4.4e1,4.6e1,4.8e1,5e1,5.2e1,5.4e1,5.6e1,5.8e1,6e1,6.2e1,6.4e1,6.6e1,6.8e1,7e1,7.2e1,7.4e1,7.6e1,7.8e1,8e1,8.2e1,8.4e1,8.6e1,8.8e1,9e1,9.2e1,9.4e1,9.6e1,9.8e1,1e2,1.02e2,1.04e2,1.06e2,1.08e2,1.1e2,1.12e2,1.14e2,1.16e2,1.18e2,1.2e2,1.22e2,1.24e2,1.26e2,1.28e2]}}},{"name":"DIVQ1","Elementtype":"devisor","sources":[{"input":{"from":"DIVN1"}},{"output":{"to":"FMCMult"}},{"output":{"to":"FDCANMult"}},{"output":{"to":"SPDIFMult"}},{"output":{"to":"SPI1Mult"}},{"output":{"to":"SPI23Mult"}},{"output":{"to":"SAI1Mult"}},{"output":{"to":"SAI2Mult"}},{"output":{"to":"MCO1Mult"}},{"output":{"to":"DIVQ1output"}}],"reference":{"Number":{"default":2,"max":128,"min":1}}},{"name":"DIVQ1output","Elementtype":"output","sources":[{"input":{"from":"DIVQ1"}}],"reference":{"FixedNumber":96000000}},{"name":"DIVR1","Elementtype":"devisor","sources":[{"input":{"from":"DIVN1"}},{"output":{"to":"DIVR1output"}}],"reference":{"Number":{"default":2,"max":128,"min":1}}},{"name":"DIVR1output","Elementtype":"output","sources":[{"input":{"from":"DIVR1"}}],"reference":{"FixedNumber":96000000}},{"name":"DIVS1","Elementtype":"devisor","sources":[{"input":{"from":"DIVN1"}},{"output":{"to":"DIVS1output"}}],"reference":{"Number":{"default":2,"max":8,"min":1}}},{"name":"DIVS1output","Elementtype":"output","sources":[{"input":{"from":"DIVS1"}}],"reference":{"FixedNumber":96000000}},{"name":"DIVT1","Elementtype":"devisor","sources":[{"input":{"from":"DIVN1"}},{"output":{"to":"DIVT1output"}}],"reference":{"Number":{"default":2,"max":8,"min":1}}},{"name":"DIVT1output","Elementtype":"output","sources":[{"input":{"from":"DIVT1"}}],"reference":{"FixedNumber":96000000}},{"name":"DIVN2","Elementtype":"multiplicatorFrac","sources":[{"input":{"from":"DIVM2"}},{"input":{"from":"PLL2FRACN"}},{"output":{"to":"DIVP2"}},{"output":{"to":"DIVQ2"}},{"output":{"to":"DIVR2"}},{"output":{"to":"DIVS2"}},{"output":{"to":"DIVT2"}}],"reference":{"Number":{"default":128,"max":420,"min":8}}},{"name":"PLL2FRACN","Elementtype":"fractional","sources":[{"output":{"to":"DIVN2"}}],"reference":{"Number":{"default":0,"max":8191,"min":0}}},{"name":"DIVP2","Elementtype":"devisor","sources":[{"input":{"from":"DIVN2"}},{"output":{"to":"SPI1Mult"}},{"output":{"to":"SPI23Mult"}},{"output":{"to":"SAI1Mult"}},{"output":{"to":"LPTIM1Mult"}},{"output":{"to":"SAI2Mult"}},{"output":{"to":"ADCMult"}},{"output":{"to":"LPTIM23Mult"}},{"output":{"to":"LPTIM45Mult"}},{"output":{"to":"FDCANMult"}},{"output":{"to":"ADFMult"}},{"output":{"to":"MCO2Mult"}},{"output":{"to":"DIVP2output"}},{"output":{"to":"ADFMult"}}],"reference":{"Number":{"default":2,"max":128,"min":1}}},{"name":"DIVP2output","Elementtype":"output","sources":[{"input":{"from":"DIVP2"}}],"reference":{"FixedNumber":96000000}},{"name":"DIVQ2","Elementtype":"devisor","sources":[{"input":{"from":"DIVN2"}},{"output":{"to":"SPI45Mult"}},{"output":{"to":"USART1Mult"}},{"output":{"to":"USART234578Mult"}},{"output":{"to":"LPUART1Mult"}},{"output":{"to":"SPI6Mult"}},{"output":{"to":"DIVQ2output"}}],"reference":{"Number":{"default":2,"max":128,"min":1}}},{"name":"DIVQ2output","Elementtype":"output","sources":[{"input":{"from":"DIVQ2"}}],"reference":{"FixedNumber":96000000}},{"name":"DIVR2","Elementtype":"devisor","sources":[{"input":{"from":"DIVN2"}},{"output":{"to":"DIVR2output"}},{"output":{"to":"FMCMult"}},{"output":{"to":"SPDIFMult"}}],"reference":{"Number":{"default":2,"max":128,"min":1}}},{"name":"DIVR2output","Elementtype":"output","sources":[{"input":{"from":"DIVR2"}}],"reference":{"FixedNumber":96000000}},{"name":"DIVS2","Elementtype":"devisor","sources":[{"input":{"from":"DIVN2"}},{"output":{"to":"DIVS2output"}},{"output":{"to":"SDMMCMult"}},{"output":{"to":"XSPI1Mult"}},{"output":{"to":"XSPI2Mult"}}],"reference":{"Number":{"default":2,"max":8,"min":1}}},{"name":"DIVS2output","Elementtype":"output","sources":[{"input":{"from":"DIVS2"}}],"reference":{"FixedNumber":96000000}},{"name":"DIVT2","Elementtype":"devisor","sources":[{"input":{"from":"DIVN2"}},{"output":{"to":"DIVT2output"}},{"output":{"to":"SDMMCMult"}},{"output":{"to":"XSPI1Mult"}},{"output":{"to":"XSPI2Mult"}}],"reference":{"Number":{"default":2,"max":8,"min":1}}},{"name":"DIVT2output","Elementtype":"output","sources":[{"input":{"from":"DIVT2"}}],"reference":{"FixedNumber":96000000}},{"name":"DIVN3","Elementtype":"multiplicatorFrac","sources":[{"input":{"from":"DIVM3"}},{"input":{"from":"PLL3FRACN"}},{"output":{"to":"DIVP3"}},{"output":{"to":"DIVQ3"}},{"output":{"to":"DIVR3"}}],"reference":{"Number":{"default":128,"max":420,"min":12}}},{"name":"PLL3FRACN","Elementtype":"fractional","sources":[{"output":{"to":"DIVN3"}}],"reference":{"Number":{"default":0,"max":8191,"min":0}}},{"name":"DIVP3","Elementtype":"devisor","sources":[{"input":{"from":"DIVN3"}},{"output":{"to":"SPI1Mult"}},{"output":{"to":"SPI23Mult"}},{"output":{"to":"SAI1Mult"}},{"output":{"to":"SAI2Mult"}},{"output":{"to":"DIVP3output"}},{"output":{"to":"ADFMult"}}],"reference":{"Number":{"default":2,"max":128,"min":1}}},{"name":"DIVP3output","Elementtype":"output","sources":[{"input":{"from":"DIVP3"}}],"reference":{"FixedNumber":96000000}},{"name":"DIVQ3","Elementtype":"devisor","sources":[{"input":{"from":"DIVN3"}},{"output":{"to":"SPI45Mult"}},{"output":{"to":"USART1Mult"}},{"output":{"to":"USART234578Mult"}},{"output":{"to":"LPUART1Mult"}},{"output":{"to":"SPI6Mult"}},{"output":{"to":"DIVQ3output"}},{"output":{"to":"USBPHYCLKMux"}},{"output":{"to":"USBOCLKMux"}},{"output":{"to":"FMCMult"}}],"reference":{"Number":{"default":2,"max":128,"min":1}}},{"name":"DIVQ3output","Elementtype":"output","sources":[{"input":{"from":"DIVQ3"}}],"reference":{"FixedNumber":96000000}},{"name":"DIVR3","Elementtype":"devisor","sources":[{"input":{"from":"DIVN3"}},{"output":{"to":"DIVR3output"}},{"output":{"to":"SPDIFMult"}},{"output":{"to":"LPTIM1Mult"}},{"output":{"to":"I2C1Mult"}},{"output":{"to":"ADCMult"}},{"output":{"to":"LPTIM23Mult"}},{"output":{"to":"LPTIM45Mult"}},{"output":{"to":"I2C23Mult"}},{"output":{"to":"PSSIMult"}},{"output":{"to":"LTDCOutput"}}],"reference":{"Number":{"default":2,"max":128,"min":1}}},{"name":"DIVR3output","Elementtype":"output","sources":[{"input":{"from":"DIVR3"}}],"reference":{"FixedNumber":96000000}},{"name":"DIVS3","Elementtype":"devisor","sources":[{"input":{"from":"DIVN3"}},{"output":{"to":"DIVS3output"}},{"output":{"to":"ETHPHYMult"}}],"reference":{"Number":{"default":2,"max":8,"min":1}}},{"name":"DIVS3output","Elementtype":"output","sources":[{"input":{"from":"DIVS3"}}],"reference":{"FixedNumber":96000000}},{"name":"DIVT3","Elementtype":"devisor","sources":[{"input":{"from":"DIVN3"}},{"output":{"to":"DIVT3output"}}],"reference":{"Number":{"default":2,"max":8,"min":1}}},{"name":"DIVT3output","Elementtype":"output","sources":[{"input":{"from":"DIVT3"}}],"reference":{"FixedNumber":96000000}},{"name":"HSERTCDevisor","Elementtype":"devisor","sources":[{"input":{"from":"HSEOSC"}},{"output":{"to":"RTCClkSource"}}],"reference":{"NumberList":{"default":2e0,"list":[2e0,3e0,4e0,5e0,6e0,7e0,8e0,9e0,1e1,1.1e1,1.2e1,1.3e1,1.4e1,1.5e1,1.6e1,1.7e1,1.8e1,1.9e1,2e1,2.1e1,2.2e1,2.3e1,2.4e1,2.5e1,2.6e1,2.7e1,2.8e1,2.9e1,3e1,3.1e1,3.2e1,3.3e1,3.4e1,3.5e1,3.6e1,3.7e1,3.8e1,3.9e1,4e1,4.1e1,4.2e1,4.3e1,4.4e1,4.5e1,4.6e1,4.7e1,4.8e1,4.9e1,5e1,5.1e1,5.2e1,5.3e1,5.4e1,5.5e1,5.6e1,5.7e1,5.8e1,5.9e1,6e1,6.1e1,6.2e1,6.3e1]}}},{"name":"RTCClkSource","Elementtype":"multiplexor","sources":[{"input":{"from":"HSERTCDevisor"}},{"input":{"from":"LSEOSC"}},{"input":{"from":"LSIRC"}},{"output":{"to":"RTCOutput"}}],"reference":{"Input":{"DefaultInput":"LSIRC"}}},{"name":"RTCOutput","Elementtype":"output","sources":[{"input":{"from":"RTCClkSource"}}],"reference":{"FixedNumber":96000000}},{"name":"IWDGOutput","Elementtype":"output","sources":[{"input":{"from":"LSIRC"}}],"reference":{"FixedNumber":32000}},{"name":"UCPDoutput","Elementtype":"output","sources":[{"input":{"from":"HSI_DIV"}}],"reference":{"FixedNumber":96000000}},{"name":"HSI_DIV","Elementtype":"devisor","sources":[{"input":{"from":"HSIRC"}},{"output":{"to":"UCPDoutput"}}],"reference":{"NumberList":{"default":4e0,"list":[4e0]}}},{"name":"SPI1Mult","Elementtype":"multiplexor","sources":[{"input":{"from":"DIVQ1"}},{"input":{"from":"DIVP2"}},{"input":{"from":"DIVP3"}},{"input":{"from":"I2S_CKIN"}},{"input":{"from":"CKPERSource"}},{"output":{"to":"SPI1output"}}],"reference":{"Input":{"DefaultInput":"DIVQ1"}}},{"name":"SPI1output","Elementtype":"activeOutput","sources":[{"input":{"from":"SPI1Mult"}}],"reference":{"FixedNumber":96000000}},{"name":"SPI23Mult","Elementtype":"multiplexor","sources":[{"input":{"from":"DIVQ1"}},{"input":{"from":"DIVP2"}},{"input":{"from":"DIVP3"}},{"input":{"from":"I2S_CKIN"}},{"input":{"from":"CKPERSource"}},{"output":{"to":"SPI23output"}}],"reference":{"Input":{"DefaultInput":"DIVQ1"}}},{"name":"SPI23output","Elementtype":"activeOutput","sources":[{"input":{"from":"SPI23Mult"}}],"reference":{"FixedNumber":96000000}},{"name":"SAI1Mult","Elementtype":"multiplexor","sources":[{"input":{"from":"DIVQ1"}},{"input":{"from":"DIVP2"}},{"input":{"from":"DIVP3"}},{"input":{"from":"I2S_CKIN"}},{"input":{"from":"CKPERSource"}},{"output":{"to":"SAI1output"}}],"reference":{"Input":{"DefaultInput":"DIVQ1"}}},{"name":"SAI1output","Elementtype":"activeOutput","sources":[{"input":{"from":"SAI1Mult"}}],"reference":{"FixedNumber":96000000}},{"name":"SAI2Mult","Elementtype":"multiplexor","sources":[{"input":{"from":"DIVQ1"}},{"input":{"from":"DIVP2"}},{"input":{"from":"DIVP3"}},{"input":{"from":"I2S_CKIN"}},{"input":{"from":"CKPERSource"}},{"input":{"from":"SPDIFMult"}},{"output":{"to":"SAI2output"}}],"reference":{"Input":{"DefaultInput":"DIVQ1"}}},{"name":"SAI2output","Elementtype":"activeOutput","sources":[{"input":{"from":"SAI2Mult"}}],"reference":{"FixedNumber":96000000}},{"name":"I2C1Mult","Elementtype":"multiplexor","sources":[{"input":{"from":"PPRE1"}},{"input":{"from":"DIVR3"}},{"input":{"from":"HSIDiv"}},{"input":{"from":"CSIRC"}},{"output":{"to":"I2C1output"}}],"reference":{"Input":{"DefaultInput":"PPRE1"}}},{"name":"I2C1output","Elementtype":"activeOutput","sources":[{"input":{"from":"I2C1Mult"}}],"reference":{"FixedNumber":96000000}},{"name":"I2C23Mult","Elementtype":"multiplexor","sources":[{"input":{"from":"PPRE1"}},{"input":{"from":"DIVR3"}},{"input":{"from":"HSIDiv"}},{"input":{"from":"CSIRC"}},{"output":{"to":"I2C23output"}}],"reference":{"Input":{"DefaultInput":"PPRE1"}}},{"name":"I2C23output","Elementtype":"activeOutput","sources":[{"input":{"from":"I2C23Mult"}}],"reference":{"FixedNumber":96000000}},{"name":"SPDIFMult","Elementtype":"multiplexor","sources":[{"input":{"from":"DIVQ1"}},{"input":{"from":"DIVR2"}},{"input":{"from":"DIVR3"}},{"input":{"from":"HSIDiv"}},{"output":{"to":"SPDIFoutput"}},{"output":{"to":"SAI2Mult"}}],"reference":{"Input":{"DefaultInput":"DIVQ1"}}},{"name":"SPDIFoutput","Elementtype":"activeOutput","sources":[{"input":{"from":"SPDIFMult"}}],"reference":{"FixedNumber":96000000}},{"name":"LTDCOutput","Elementtype":"activeOutput","sources":[{"input":{"from":"DIVR3"}}],"reference":{"FixedNumber":96000000}},{"name":"FMCMult","Elementtype":"multiplexor","sources":[{"input":{"from":"AHB5Output"}},{"input":{"from":"DIVQ1"}},{"input":{"from":"DIVR2"}},{"input":{"from":"HSIRC"}},{"output":{"to":"FMCoutput"}}],"reference":{"Input":{"DefaultInput":"AHB5Output"}}},{"name":"FMCoutput","Elementtype":"activeOutput","sources":[{"input":{"from":"FMCMult"}}],"reference":{"FixedNumber":96000000}},{"name":"SDMMCMult","Elementtype":"multiplexor","sources":[{"input":{"from":"DIVS2"}},{"input":{"from":"DIVT2"}},{"output":{"to":"SDMMCoutput"}}],"reference":{"Input":{"DefaultInput":"DIVS2"}}},{"name":"SDMMCoutput","Elementtype":"activeOutput","sources":[{"input":{"from":"SDMMCMult"}}],"reference":{"Number":{"default":96000000,"max":200000000,"min":0}}},{"name":"USART1Mult","Elementtype":"multiplexor","sources":[{"input":{"from":"PPRE2"}},{"input":{"from":"DIVQ2"}},{"input":{"from":"DIVQ3"}},{"input":{"from":"HSIDiv"}},{"input":{"from":"CSIRC"}},{"input":{"from":"LSEOSC"}},{"output":{"to":"USART1output"}}],"reference":{"Input":{"DefaultInput":"PPRE2"}}},{"name":"USART1output","Elementtype":"activeOutput","sources":[{"input":{"from":"USART1Mult"}}],"reference":{"FixedNumber":96000000}},{"name":"ADFMult","Elementtype":"multiplexor","sources":[{"input":{"from":"AHBOutput"}},{"input":{"from":"DIVP2"}},{"input":{"from":"DIVP3"}},{"input":{"from":"I2S_CKIN"}},{"input":{"from":"CSIRC"}},{"input":{"from":"HSIDiv"}},{"output":{"to":"ADFoutput"}}],"reference":{"Input":{"DefaultInput":"AHBOutput"}}},{"name":"ADFoutput","Elementtype":"activeOutput","sources":[{"input":{"from":"ADFMult"}}],"reference":{"FixedNumber":96000000}},{"name":"USART234578Mult","Elementtype":"multiplexor","sources":[{"input":{"from":"PPRE1"}},{"input":{"from":"DIVQ2"}},{"input":{"from":"DIVQ3"}},{"input":{"from":"HSIDiv"}},{"input":{"from":"CSIRC"}},{"input":{"from":"LSEOSC"}},{"output":{"to":"USART234578output"}}],"reference":{"Input":{"DefaultInput":"PPRE1"}}},{"name":"USART234578output","Elementtype":"activeOutput","sources":[{"input":{"from":"USART234578Mult"}}],"reference":{"FixedNumber":96000000}},{"name":"LPUART1Mult","Elementtype":"multiplexor","sources":[{"input":{"from":"PPRE4"}},{"input":{"from":"DIVQ2"}},{"input":{"from":"DIVQ3"}},{"input":{"from":"HSIDiv"}},{"input":{"from":"CSIRC"}},{"input":{"from":"LSEOSC"}},{"output":{"to":"LPUART1output"}}],"reference":{"Input":{"DefaultInput":"PPRE4"}}},{"name":"LPUART1output","Elementtype":"activeOutput","sources":[{"input":{"from":"LPUART1Mult"}}],"reference":{"FixedNumber":96000000}},{"name":"LPTIM1Mult","Elementtype":"multiplexor","sources":[{"input":{"from":"PPRE1"}},{"input":{"from":"DIVP2"}},{"input":{"from":"DIVR3"}},{"input":{"from":"LSEOSC"}},{"input":{"from":"LSIRC"}},{"input":{"from":"CKPERSource"}},{"output":{"to":"LPTIM1output"}}],"reference":{"Input":{"DefaultInput":"PPRE1"}}},{"name":"LPTIM1output","Elementtype":"activeOutput","sources":[{"input":{"from":"LPTIM1Mult"}}],"reference":{"FixedNumber":96000000}},{"name":"LPTIM23Mult","Elementtype":"multiplexor","sources":[{"input":{"from":"PPRE4"}},{"input":{"from":"DIVP2"}},{"input":{"from":"DIVR3"}},{"input":{"from":"LSEOSC"}},{"input":{"from":"LSIRC"}},{"input":{"from":"CKPERSource"}},{"output":{"to":"LPTIM23output"}}],"reference":{"Input":{"DefaultInput":"PPRE4"}}},{"name":"LPTIM23output","Elementtype":"activeOutput","sources":[{"input":{"from":"LPTIM23Mult"}}],"reference":{"FixedNumber":96000000}},{"name":"LPTIM45Mult","Elementtype":"multiplexor","sources":[{"input":{"from":"PPRE4"}},{"input":{"from":"DIVP2"}},{"input":{"from":"DIVR3"}},{"input":{"from":"LSEOSC"}},{"input":{"from":"LSIRC"}},{"input":{"from":"CKPERSource"}},{"output":{"to":"LPTIM45output"}}],"reference":{"Input":{"DefaultInput":"PPRE4"}}},{"name":"LPTIM45output","Elementtype":"activeOutput","sources":[{"input":{"from":"LPTIM45Mult"}}],"reference":{"FixedNumber":96000000}},{"name":"SPI6Mult","Elementtype":"multiplexor","sources":[{"input":{"from":"PPRE4"}},{"input":{"from":"DIVQ2"}},{"input":{"from":"DIVQ3"}},{"input":{"from":"HSIDiv"}},{"input":{"from":"CSIRC"}},{"input":{"from":"HSEOSC"}},{"output":{"to":"SPI6output"}}],"reference":{"Input":{"DefaultInput":"PPRE4"}}},{"name":"SPI6output","Elementtype":"activeOutput","sources":[{"input":{"from":"SPI6Mult"}}],"reference":{"FixedNumber":96000000}},{"name":"SPI45Mult","Elementtype":"multiplexor","sources":[{"input":{"from":"PPRE2"}},{"input":{"from":"DIVQ2"}},{"input":{"from":"DIVQ3"}},{"input":{"from":"HSIDiv"}},{"input":{"from":"CSIRC"}},{"input":{"from":"HSEOSC"}},{"output":{"to":"SPI45output"}}],"reference":{"Input":{"DefaultInput":"PPRE2"}}},{"name":"SPI45output","Elementtype":"activeOutput","sources":[{"input":{"from":"SPI45Mult"}}],"reference":{"FixedNumber":96000000}},{"name":"HSEUSBPHYDevisor","Elementtype":"devisor","sources":[{"input":{"from":"HSEOSC"}},{"output":{"to":"USBPHYCLKMux"}}],"reference":{"NumberList":{"default":2e0,"list":[2e0]}}},{"name":"USBPHYCLKMux","Elementtype":"multiplexor","sources":[{"input":{"from":"HSEOSC"}},{"input":{"from":"HSEUSBPHYDevisor"}},{"input":{"from":"DIVQ3"}},{"output":{"to":"USBPHYCLKOutput"}},{"output":{"to":"USBPHYRC"}},{"output":{"to":"USBPHYRC60"}}],"reference":{"Input":{"DefaultInput":"HSEOSC"}}},{"name":"USBPHYCLKOutput","Elementtype":"activeOutput","sources":[{"input":{"from":"USBPHYCLKMux"}}],"reference":{"NumberList":{"default":1.92e7,"list":[1.6e7,1.92e7,2e7,2.4e7,2.6e7,3.2e7]}}},{"name":"USBPHYRC","Elementtype":"fixedSource","sources":[{"output":{"to":"USBOCLKMux"}}],"reference":{"FixedNumber":48000000}},{"name":"USBPHYRC60","Elementtype":"fixedSource","sources":[],"reference":{"FixedNumber":60000000}},{"name":"USBOCLKMux","Elementtype":"multiplexor","sources":[{"input":{"from":"RC48"}},{"input":{"from":"DIVQ3"}},{"input":{"from":"HSEOSC"}},{"input":{"from":"USBPHYRC"}},{"output":{"to":"USBOFSCLKOutput"}}],"reference":{"Input":{"DefaultInput":"RC48"}}},{"name":"USBOFSCLKOutput","Elementtype":"activeOutput","sources":[{"input":{"from":"USBOCLKMux"}}],"reference":{"FixedNumber":96000000}},{"name":"RNGOutput","Elementtype":"output","sources":[{"input":{"from":"RC48"}}],"reference":{"Number":{"default":48000000,"max":48000000,"min":0}}},{"name":"DTSOutput","Elementtype":"output","sources":[{"input":{"from":"LSEOSC"}}],"reference":{"Number":{"default":60000000,"max":90000000,"min":0}}},{"name":"FDCANMult","Elementtype":"multiplexor","sources":[{"input":{"from":"HSEOSC"}},{"input":{"from":"DIVQ1"}},{"input":{"from":"DIVP2"}},{"output":{"to":"FDCANoutput"}}],"reference":{"Input":{"DefaultInput":"HSEOSC"}}},{"name":"FDCANoutput","Elementtype":"activeOutput","sources":[{"input":{"from":"FDCANMult"}}],"reference":{"FixedNumber":96000000}},{"name":"XSPI1Mult","Elementtype":"multiplexor","sources":[{"input":{"from":"AHB5Output"}},{"input":{"from":"DIVS2"}},{"input":{"from":"DIVT2"}},{"output":{"to":"XSPI1output"}}],"reference":{"Input":{"DefaultInput":"AHB5Output"}}},{"name":"XSPI1output","Elementtype":"activeOutput","sources":[{"input":{"from":"XSPI1Mult"}}],"reference":{"FixedNumber":96000000}},{"name":"PSSIMult","Elementtype":"multiplexor","sources":[{"input":{"from":"DIVR3"}},{"input":{"from":"CKPERSource"}},{"output":{"to":"PSSIoutput"}}],"reference":{"Input":{"DefaultInput":"DIVR3"}}},{"name":"PSSIoutput","Elementtype":"activeOutput","sources":[{"input":{"from":"PSSIMult"}}],"reference":{"FixedNumber":100000000}},{"name":"XSPI2Mult","Elementtype":"multiplexor","sources":[{"input":{"from":"AHB5Output"}},{"input":{"from":"DIVS2"}},{"input":{"from":"DIVT2"}},{"output":{"to":"XSPI2output"}}],"reference":{"Input":{"DefaultInput":"AHB5Output"}}},{"name":"XSPI2output","Elementtype":"activeOutput","sources":[{"input":{"from":"XSPI2Mult"}}],"reference":{"FixedNumber":96000000}},{"name":"ETHPHYMult","Elementtype":"multiplexor","sources":[{"input":{"from":"HSEOSC"}},{"input":{"from":"DIVS3"}},{"output":{"to":"ETHPHYoutput"}},{"output":{"to":"ETH1Mult"}}],"reference":{"Input":{"DefaultInput":"HSEOSC"}}},{"name":"ETHPHYoutput","Elementtype":"activeOutput","sources":[{"input":{"from":"ETHPHYMult"}}],"reference":{"Number":{"default":100000000,"max":50000000,"min":25000000}}},{"name":"ETH1Mult","Elementtype":"multiplexor","sources":[{"input":{"from":"Dig_CKIN"}},{"input":{"from":"HSEOSC"}},{"input":{"from":"ETHPHYMult"}},{"output":{"to":"ETH1output"}}],"reference":{"Input":{"DefaultInput":"Dig_CKIN"}}},{"name":"ETH1output","Elementtype":"activeOutput","sources":[{"input":{"from":"ETH1Mult"}}],"reference":{"FixedNumber":100000000}},{"name":"ADCMult","Elementtype":"multiplexor","sources":[{"input":{"from":"DIVP2"}},{"input":{"from":"DIVR3"}},{"input":{"from":"CKPERSource"}},{"output":{"to":"ADCoutput"}}],"reference":{"Input":{"DefaultInput":"DIVP2"}}},{"name":"ADCoutput","Elementtype":"activeOutput","sources":[{"input":{"from":"ADCMult"}}],"reference":{"FixedNumber":96000000}},{"name":"CECMult","Elementtype":"multiplexor","sources":[{"input":{"from":"LSEOSC"}},{"input":{"from":"LSIRC"}},{"input":{"from":"CSICECDevisor"}},{"output":{"to":"CECoutput"}}],"reference":{"Input":{"DefaultInput":"LSEOSC"}}},{"name":"CECoutput","Elementtype":"activeOutput","sources":[{"input":{"from":"CECMult"}}],"reference":{"FixedNumber":96000000}},{"name":"CSICECDevisor","Elementtype":"devisor","sources":[{"input":{"from":"CSIRC"}},{"output":{"to":"CECMult"}}],"reference":{"NumberList":{"default":1.22e2,"list":[1.22e2]}}}]}